pyfield/__init__.py
pyfield/error.py
pyfield/field/__init__.py
pyfield/field/boolean.py
pyfield/field/integer.py
pyfield/field/real_number.py
pyfield/field/text.py
pyfield/validator/__init__.py
pyfield/validator/text.py
pyfield-0.1.3.dist-info/LICENSE.txt
pyfield-0.1.3.dist-info/WHEEL
pyfield-0.1.3.dist-info/METADATA
pyfield-0.1.3.dist-info/RECORD
