Metadata-Version: 2.1
Name: pyfield
Version: 0.1.3
Summary: Collection of field for your form
Home-page: https://github.com/Ublimjo/pyfield
License: MIT
Author: Ublim
Author-email: ublimjo@gmail.com
Classifier: License :: OSI Approved :: MIT License
Classifier: Programming Language :: Python :: 2
Classifier: Programming Language :: Python :: 2.7
Classifier: Programming Language :: Python :: 3
Classifier: Programming Language :: Python :: 3.4
Classifier: Programming Language :: Python :: 3.5
Classifier: Programming Language :: Python :: 3.6
Classifier: Programming Language :: Python :: 3.7
